lingcage/__init__.py
lingcage-0.0.1.dist-info/LICENSE
lingcage-0.0.1.dist-info/METADATA
lingcage-0.0.1.dist-info/WHEEL
lingcage-0.0.1.dist-info/top_level.txt
lingcage-0.0.1.dist-info/RECORD
