Metadata-Version: 2.1
Name: lingcage
Version: 0.0.1
Summary: A placeholder package for lingcage
Home-page: https://github.com/opensourcelater/lingcage
Author: opensourcelater
Author-email: opensourcelater@example.com
License: Apache Software License
Classifier: Programming Language :: Python :: 3
Classifier: License :: OSI Approved :: Apache Software License
Classifier: Operating System :: OS Independent
Requires-Python: >=3.6
License-File: LICENSE
